{
  "address": "BETTYxvFKRvF9ov3r7rNcW6nFLm5Kmmy3JdXzM1LgB56",
  "metadata": {
    "name": "betting_dapp",
    "version": "0.1.0",
    "spec": "0.1.0",
    "description": "Solana prediction market for betting on binary outcomes"
  },
  "instructions": [
    {
      "name": "claim_winnings",
      "discriminator": [
        161,
        215,
        24,
        59,
        14,
        236,
        242,
        221
      ],
      "accounts": [
        {
          "name": "platform",
          "writable": true
        },
        {
          "name": "market"
        },
        {
          "name": "user_position",
          "writable": true,
          "pda": {
            "seeds": [
              {
                "kind": "const",
                "value": [
                  112,
                  111,
                  115,
                  105,
                  116,
                  105,
                  111,
                  110
                ]
              },
              {
                "kind": "account",
                "path": "market"
              },
              {
                "kind": "account",
                "path": "user"
              }
            ]
          }
        },
        {
          "name": "user",
          "signer": true
        },
        {
          "name": "user_token_account",
          "writable": true
        },
        {
          "name": "yes_pool_account",
          "writable": true
        },
        {
          "name": "no_pool_account",
          "writable": true
        },
        {
          "name": "fee_account",
          "writable": true
        },
        {
          "name": "token_program",
          "address": "TokenkegQfeZyiNwAJbNbGKPFXCWuBvf9Ss623VQ5DA"
        },
        {
          "name": "system_program",
          "address": "11111111111111111111111111111111"
        }
      ],
      "args": []
    },
    {
      "name": "create_market",
      "discriminator": [
        103,
        226,
        97,
        235,
        200,
        188,
        251,
        254
      ],
      "accounts": [
        {
          "name": "platform",
          "writable": true
        },
        {
          "name": "market",
          "writable": true,
          "pda": {
            "seeds": [
              {
                "kind": "const",
                "value": [
                  109,
                  97,
                  114,
                  107,
                  101,
                  116
                ]
              },
              {
                "kind": "account",
                "path": "creator"
              },
              {
                "kind": "arg",
                "path": "title"
              }
            ]
          }
        },
        {
          "name": "creator",
          "writable": true,
          "signer": true
        },
        {
          "name": "creator_token_account",
          "writable": true
        },
        {
          "name": "yes_pool_account",
          "writable": true,
          "signer": true
        },
        {
          "name": "no_pool_account",
          "writable": true,
          "signer": true
        },
        {
          "name": "token_mint"
        },
        {
          "name": "token_program",
          "address": "TokenkegQfeZyiNwAJbNbGKPFXCWuBvf9Ss623VQ5DA"
        },
        {
          "name": "system_program",
          "address": "11111111111111111111111111111111"
        },
        {
          "name": "rent",
          "address": "SysvarRent111111111111111111111111111111111"
        }
      ],
      "args": [
        {
          "name": "title",
          "type": "string"
        },
        {
          "name": "description",
          "type": "string"
        },
        {
          "name": "closing_date",
          "type": "i64"
        },
        {
          "name": "resolution_deadline",
          "type": "i64"
        },
        {
          "name": "initial_liquidity",
          "type": "u64"
        }
      ]
    },
    {
      "name": "initialize",
      "discriminator": [
        175,
        175,
        109,
        31,
        13,
        152,
        155,
        237
      ],
      "accounts": [
        {
          "name": "platform",
          "writable": true,
          "signer": true
        },
        {
          "name": "authority",
          "writable": true,
          "signer": true
        },
        {
          "name": "system_program",
          "address": "11111111111111111111111111111111"
        }
      ],
      "args": [
        {
          "name": "fee_percentage",
          "type": "u8"
        }
      ]
    },
    {
      "name": "place_bet",
      "discriminator": [
        222,
        62,
        67,
        220,
        63,
        166,
        126,
        33
      ],
      "accounts": [
        {
          "name": "platform",
          "writable": true
        },
        {
          "name": "market",
          "writable": true
        },
        {
          "name": "user_position",
          "writable": true,
          "pda": {
            "seeds": [
              {
                "kind": "const",
                "value": [
                  112,
                  111,
                  115,
                  105,
                  116,
                  105,
                  111,
                  110
                ]
              },
              {
                "kind": "account",
                "path": "market"
              },
              {
                "kind": "account",
                "path": "user"
              }
            ]
          }
        },
        {
          "name": "user",
          "writable": true,
          "signer": true
        },
        {
          "name": "user_token_account",
          "writable": true
        },
        {
          "name": "yes_pool_account",
          "writable": true
        },
        {
          "name": "no_pool_account",
          "writable": true
        },
        {
          "name": "token_program",
          "address": "TokenkegQfeZyiNwAJbNbGKPFXCWuBvf9Ss623VQ5DA"
        },
        {
          "name": "system_program",
          "address": "11111111111111111111111111111111"
        }
      ],
      "args": [
        {
          "name": "amount",
          "type": "u64"
        },
        {
          "name": "outcome",
          "type": {
            "defined": {
              "name": "Outcome"
            }
          }
        }
      ]
    },
    {
      "name": "resolve_market",
      "discriminator": [
        155,
        23,
        80,
        173,
        46,
        74,
        23,
        239
      ],
      "accounts": [
        {
          "name": "market",
          "writable": true
        },
        {
          "name": "creator",
          "signer": true
        },
        {
          "name": "system_program",
          "address": "11111111111111111111111111111111"
        }
      ],
      "args": [
        {
          "name": "outcome",
          "type": {
            "defined": {
              "name": "Outcome"
            }
          }
        }
      ]
    }
  ],
  "accounts": [
    {
      "name": "Market",
      "discriminator": [
        219,
        190,
        213,
        55,
        0,
        227,
        198,
        154
      ]
    },
    {
      "name": "Platform",
      "discriminator": [
        77,
        92,
        204,
        58,
        187,
        98,
        91,
        12
      ]
    },
    {
      "name": "UserPosition",
      "discriminator": [
        251,
        248,
        209,
        245,
        83,
        234,
        17,
        27
      ]
    }
  ],
  "events": [
    {
      "name": "BetPlacedEvent",
      "discriminator": [
        218,
        76,
        236,
        147,
        222,
        135,
        81,
        43
      ]
    },
    {
      "name": "MarketCreatedEvent",
      "discriminator": [
        130,
        142,
        5,
        16,
        107,
        160,
        73,
        124
      ]
    },
    {
      "name": "MarketResolvedEvent",
      "discriminator": [
        87,
        249,
        34,
        139,
        194,
        159,
        14,
        156
      ]
    },
    {
      "name": "WinningsClaimedEvent",
      "discriminator": [
        30,
        231,
        120,
        152,
        158,
        82,
        26,
        135
      ]
    }
  ],
  "errors": [
    {
      "code": 6000,
      "name": "TitleTooLong",
      "msg": "Title too long, maximum 100 characters"
    },
    {
      "code": 6001,
      "name": "DescriptionTooLong",
      "msg": "Description too long, maximum 500 characters"
    },
    {
      "code": 6002,
      "name": "InvalidClosingDate",
      "msg": "Invalid closing date, must be in the future"
    },
    {
      "code": 6003,
      "name": "InvalidResolutionDeadline",
      "msg": "Invalid resolution deadline, must be after closing date"
    },
    {
      "code": 6004,
      "name": "MarketNotOpen",
      "msg": "Market is not open for betting"
    },
    {
      "code": 6005,
      "name": "MarketClosed",
      "msg": "Market is closed for betting"
    },
    {
      "code": 6006,
      "name": "InvalidBetAmount",
      "msg": "Invalid bet amount, must be greater than 0"
    },
    {
      "code": 6007,
      "name": "MarketNotResolved",
      "msg": "Market is not yet resolved"
    },
    {
      "code": 6008,
      "name": "MarketAlreadyResolved",
      "msg": "Market is already resolved"
    },
    {
      "code": 6009,
      "name": "NotMarketCreator",
      "msg": "Only the market creator can resolve the market"
    },
    {
      "code": 6010,
      "name": "MarketStillOpen",
      "msg": "Market is still open for betting"
    },
    {
      "code": 6011,
      "name": "ResolutionDeadlinePassed",
      "msg": "Resolution deadline has passed"
    },
    {
      "code": 6012,
      "name": "AlreadyClaimed",
      "msg": "Winnings have already been claimed"
    },
    {
      "code": 6013,
      "name": "PayoutTooLarge",
      "msg": "Payout too large, exceeds maximum value"
    },
    {
      "code": 6014,
      "name": "InvalidFeePercentage",
      "msg": "Fee percentage must be between 0 and 5"
    }
  ],
  "types": [
    {
      "name": "BetPlacedEvent",
      "type": {
        "kind": "struct",
        "fields": [
          {
            "name": "market_id",
            "type": "pubkey"
          },
          {
            "name": "user",
            "type": "pubkey"
          },
          {
            "name": "amount",
            "type": "u64"
          },
          {
            "name": "outcome",
            "type": {
              "defined": {
                "name": "Outcome"
              }
            }
          }
        ]
      }
    },
    {
      "name": "Market",
      "type": {
        "kind": "struct",
        "fields": [
          {
            "name": "creator",
            "type": "pubkey"
          },
          {
            "name": "title",
            "type": "string"
          },
          {
            "name": "description",
            "type": "string"
          },
          {
            "name": "closing_date",
            "type": "i64"
          },
          {
            "name": "resolution_deadline",
            "type": "i64"
          },
          {
            "name": "yes_pool",
            "type": "u64"
          },
          {
            "name": "no_pool",
            "type": "u64"
          },
          {
            "name": "total_liquidity",
            "type": "u64"
          },
          {
            "name": "status",
            "type": {
              "defined": {
                "name": "MarketStatus"
              }
            }
          },
          {
            "name": "outcome",
            "type": {
              "option": {
                "defined": {
                  "name": "Outcome"
                }
              }
            }
          },
          {
            "name": "created_at",
            "type": "i64"
          },
          {
            "name": "bump",
            "type": "u8"
          }
        ]
      }
    },
    {
      "name": "MarketCreatedEvent",
      "type": {
        "kind": "struct",
        "fields": [
          {
            "name": "market_id",
            "type": "pubkey"
          },
          {
            "name": "creator",
            "type": "pubkey"
          },
          {
            "name": "title",
            "type": "string"
          },
          {
            "name": "closing_date",
            "type": "i64"
          },
          {
            "name": "initial_liquidity",
            "type": "u64"
          }
        ]
      }
    },
    {
      "name": "MarketResolvedEvent",
      "type": {
        "kind": "struct",
        "fields": [
          {
            "name": "market_id",
            "type": "pubkey"
          },
          {
            "name": "outcome",
            "type": {
              "defined": {
                "name": "Outcome"
              }
            }
          }
        ]
      }
    },
    {
      "name": "MarketStatus",
      "type": {
        "kind": "enum",
        "variants": [
          {
            "name": "Open"
          },
          {
            "name": "Resolved"
          }
        ]
      }
    },
    {
      "name": "Outcome",
      "type": {
        "kind": "enum",
        "variants": [
          {
            "name": "Yes"
          },
          {
            "name": "No"
          }
        ]
      }
    },
    {
      "name": "Platform",
      "type": {
        "kind": "struct",
        "fields": [
          {
            "name": "authority",
            "type": "pubkey"
          },
          {
            "name": "fee_percentage",
            "type": "u8"
          },
          {
            "name": "total_markets",
            "type": "u64"
          },
          {
            "name": "total_volume",
            "type": "u64"
          }
        ]
      }
    },
    {
      "name": "UserPosition",
      "type": {
        "kind": "struct",
        "fields": [
          {
            "name": "market",
            "type": "pubkey"
          },
          {
            "name": "user",
            "type": "pubkey"
          },
          {
            "name": "yes_bets",
            "type": "u64"
          },
          {
            "name": "no_bets",
            "type": "u64"
          },
          {
            "name": "total_staked",
            "type": "u64"
          },
          {
            "name": "claimed",
            "type": "bool"
          },
          {
            "name": "is_initialized",
            "type": "bool"
          },
          {
            "name": "bump",
            "type": "u8"
          }
        ]
      }
    },
    {
      "name": "WinningsClaimedEvent",
      "type": {
        "kind": "struct",
        "fields": [
          {
            "name": "market_id",
            "type": "pubkey"
          },
          {
            "name": "user",
            "type": "pubkey"
          },
          {
            "name": "amount",
            "type": "u64"
          }
        ]
      }
    }
  ]
}